[
  {
    "transaction_date": "2022-10-01",
    "description": "Work Email",
    "merchant": "Google",
    "amount": 6.36,
    "currency": "USD",
    "payment_method": "Credit Card: Chase Sapphire Reserve",
    "transaction_type": "expense",
    "tags": [],
    "metadata": {
      "source": "Expense Tracker",
      "line_number": 9836,
      "reimbursable": false,
      "business_expense_marker": false
    }
  },
  {
    "transaction_date": "2022-10-01",
    "description": "This Month’s Rent, Storage, Internet, PECO (Conshy)",
    "merchant": "Jordan",
    "amount": 887,
    "currency": "USD",
    "payment_method": "PNC Bank Account",
    "transaction_type": "expense",
    "tags": [],
    "metadata": {
      "source": "Expense Tracker",
      "line_number": 9837,
      "reimbursable": false,
      "business_expense_marker": false
    }
  },
  {
    "transaction_date": "2022-10-01",
    "description": "Additional Greens Fee Cost",
    "merchant": "Marina Bay",
    "amount": 32.94,
    "currency": "USD",
    "payment_method": "Credit Card: Chase Sapphire Reserve",
    "transaction_type": "expense",
    "tags": [],
    "metadata": {
      "source": "Expense Tracker",
      "line_number": 9839,
      "reimbursable": true,
      "business_expense_marker": false
    }
  },
  {
    "transaction_date": "2022-10-01",
    "description": "Transfer Fee",
    "merchant": "Wise",
    "amount": 5.64,
    "currency": "USD",
    "payment_method": "PNC Bank Account",
    "transaction_type": "expense",
    "tags": [],
    "metadata": {
      "source": "Expense Tracker",
      "line_number": 9840,
      "reimbursable": false,
      "business_expense_marker": false
    }
  },
  {
    "transaction_date": "2022-10-01",
    "description": "Lunch",
    "merchant": "canopy Cafe",
    "amount": 12.68,
    "currency": "USD",
    "payment_method": "Credit Card: Chase Sapphire Reserve",
    "transaction_type": "expense",
    "tags": [],
    "metadata": {
      "source": "Expense Tracker",
      "line_number": 9843,
      "reimbursable": false,
      "business_expense_marker": false
    }
  },
  {
    "transaction_date": "2022-10-01",
    "description": "Hotel: Singapore",
    "merchant": "Agoda",
    "amount": 361.34,
    "currency": "USD",
    "payment_method": "Credit Card: Chase Sapphire Reserve",
    "transaction_type": "expense",
    "tags": [],
    "metadata": {
      "source": "Expense Tracker",
      "line_number": 9844,
      "reimbursable": true,
      "business_expense_marker": false
    }
  },
  {
    "transaction_date": "2022-10-01",
    "description": "taxi to hotel",
    "merchant": "GoJek",
    "amount": 15.6,
    "currency": "USD",
    "payment_method": "Credit Card: Chase Sapphire Reserve",
    "transaction_type": "expense",
    "tags": [],
    "metadata": {
      "source": "Expense Tracker",
      "line_number": 9845,
      "reimbursable": false,
      "business_expense_marker": false
    }
  },
  {
    "transaction_date": "2022-10-01",
    "description": "Dinner",
    "merchant": "CALI, Citadines",
    "amount": 37.78,
    "currency": "USD",
    "payment_method": "Credit Card: Chase Sapphire Reserve",
    "transaction_type": "expense",
    "tags": [],
    "metadata": {
      "source": "Expense Tracker",
      "line_number": 9847,
      "reimbursable": false,
      "business_expense_marker": false
    }
  },
  {
    "transaction_date": "2022-10-01",
    "description": "Taxi: Bar to Checkpoint",
    "merchant": "GoJek",
    "amount": 33.6,
    "currency": "USD",
    "payment_method": "Credit Card: Chase Sapphire Reserve",
    "transaction_type": "expense",
    "tags": [],
    "metadata": {
      "source": "Expense Tracker",
      "line_number": 9848,
      "reimbursable": false,
      "business_expense_marker": false
    }
  },
  {
    "transaction_date": "2022-10-01",
    "description": "Taxi to Hotel (JB)",
    "merchant": "Grab",
    "amount": 1.08,
    "currency": "USD",
    "payment_method": "Credit Card: Chase Sapphire Reserve",
    "transaction_type": "expense",
    "tags": [],
    "metadata": {
      "source": "Expense Tracker",
      "line_number": 9849,
      "reimbursable": false,
      "business_expense_marker": false
    }
  },
  {
    "transaction_date": "2022-10-01",
    "description": "Taxi to Warren",
    "merchant": "Grab",
    "amount": 10.28,
    "currency": "USD",
    "payment_method": "Credit Card: Chase Sapphire Reserve",
    "transaction_type": "expense",
    "tags": [],
    "metadata": {
      "source": "Expense Tracker",
      "line_number": 9850,
      "reimbursable": false,
      "business_expense_marker": false
    }
  },
  {
    "transaction_date": "2022-10-02",
    "description": "Hotel: Johor Bahru",
    "merchant": "Holiday Inn Express",
    "amount": 220.08,
    "currency": "USD",
    "payment_method": "Credit Card: Chase Sapphire Reserve",
    "transaction_type": "expense",
    "tags": [],
    "metadata": {
      "source": "Expense Tracker",
      "line_number": 9853,
      "reimbursable": false,
      "business_expense_marker": false
    }
  },
  {
    "transaction_date": "2022-10-02",
    "description": "Taxi: Hotel to Exchange to Checkpoint",
    "merchant": "Grab",
    "amount": 5.19,
    "currency": "USD",
    "payment_method": "Credit Card: Chase Sapphire Reserve",
    "transaction_type": "expense",
    "tags": [],
    "metadata": {
      "source": "Expense Tracker",
      "line_number": 9854,
      "reimbursable": false,
      "business_expense_marker": false
    }
  },
  {
    "transaction_date": "2022-10-02",
    "description": "Taxi: Checkpoint to Hotel",
    "merchant": "Grab",
    "amount": 13.15,
    "currency": "USD",
    "payment_method": "Credit Card: Chase Sapphire Reserve",
    "transaction_type": "expense",
    "tags": [],
    "metadata": {
      "source": "Expense Tracker",
      "line_number": 9855,
      "reimbursable": false,
      "business_expense_marker": false
    }
  },
  {
    "transaction_date": "2022-10-02",
    "description": "Drinks",
    "merchant": "Formula 1",
    "amount": 20.99,
    "currency": "USD",
    "payment_method": "Credit Card: Chase Sapphire Reserve",
    "transaction_type": "expense",
    "tags": [],
    "metadata": {
      "source": "Expense Tracker",
      "line_number": 9856,
      "reimbursable": false,
      "business_expense_marker": false
    }
  },
  {
    "transaction_date": "2022-10-02",
    "description": "Dinner",
    "merchant": "Sands",
    "amount": 24,
    "currency": "USD",
    "payment_method": "Credit Card: Chase Sapphire Reserve",
    "transaction_type": "expense",
    "tags": [],
    "metadata": {
      "source": "Expense Tracker",
      "line_number": 9858,
      "reimbursable": false,
      "business_expense_marker": false
    }
  },
  {
    "transaction_date": "2022-10-03",
    "description": "Hotel",
    "merchant": "Duangtawan",
    "amount": 37.46,
    "currency": "USD",
    "payment_method": "Credit Card: Chase Sapphire Reserve",
    "transaction_type": "expense",
    "tags": [],
    "metadata": {
      "source": "Expense Tracker",
      "line_number": 9864,
      "reimbursable": false,
      "business_expense_marker": false
    }
  },
  {
    "transaction_date": "2022-10-04",
    "description": "Hotel",
    "merchant": "Duangtawan",
    "amount": 37.46,
    "currency": "USD",
    "payment_method": "Credit Card: Chase Sapphire Reserve",
    "transaction_type": "expense",
    "tags": [],
    "metadata": {
      "source": "Expense Tracker",
      "line_number": 9871,
      "reimbursable": false,
      "business_expense_marker": false
    }
  },
  {
    "transaction_date": "2022-10-04",
    "description": "Clothes",
    "merchant": "Lotus’",
    "amount": 14.46,
    "currency": "USD",
    "payment_method": "Credit Card: Chase Sapphire Reserve",
    "transaction_type": "expense",
    "tags": [],
    "metadata": {
      "source": "Expense Tracker",
      "line_number": 9876,
      "reimbursable": false,
      "business_expense_marker": false
    }
  },
  {
    "transaction_date": "2022-10-05",
    "description": "Grab to golf",
    "merchant": "Unknown",
    "amount": 2.31,
    "currency": "USD",
    "payment_method": "Credit Card: Chase Sapphire Reserve",
    "transaction_type": "expense",
    "tags": [],
    "metadata": {
      "source": "Expense Tracker",
      "line_number": 9882,
      "reimbursable": false,
      "business_expense_marker": false
    }
  },
  {
    "transaction_date": "2022-10-05",
    "description": "Taxi to Hotel",
    "merchant": "Grab",
    "amount": 2.43,
    "currency": "USD",
    "payment_method": "Credit Card: Chase Sapphire Reserve",
    "transaction_type": "expense",
    "tags": [],
    "metadata": {
      "source": "Expense Tracker",
      "line_number": 9887,
      "reimbursable": false,
      "business_expense_marker": false
    }
  },
  {
    "transaction_date": "2022-10-06",
    "description": "Hotel",
    "merchant": "Duangtawan",
    "amount": 77.1,
    "currency": "USD",
    "payment_method": "Credit Card: Chase Sapphire Reserve",
    "transaction_type": "expense",
    "tags": [],
    "metadata": {
      "source": "Expense Tracker",
      "line_number": 9899,
      "reimbursable": false,
      "business_expense_marker": false
    }
  },
  {
    "transaction_date": "2022-10-06",
    "description": "Taxi to Hotel",
    "merchant": "Grab",
    "amount": 3.66,
    "currency": "USD",
    "payment_method": "Bangkok Bank Account",
    "transaction_type": "expense",
    "tags": [],
    "metadata": {
      "source": "Expense Tracker",
      "line_number": 9905,
      "reimbursable": false,
      "business_expense_marker": false
    }
  },
  {
    "transaction_date": "2022-10-06",
    "description": "Flight: CNX - BKK",
    "merchant": "AirAsia",
    "amount": 84.21,
    "currency": "USD",
    "payment_method": "Credit Card: Chase Sapphire Reserve",
    "transaction_type": "expense",
    "tags": [],
    "metadata": {
      "source": "Expense Tracker",
      "line_number": 9907,
      "reimbursable": false,
      "business_expense_marker": false
    }
  },
  {
    "transaction_date": "2022-10-06",
    "description": "Flight: BKK - CNX",
    "merchant": "AirAsia",
    "amount": 88.44,
    "currency": "USD",
    "payment_method": "Credit Card: Chase Sapphire Reserve",
    "transaction_type": "expense",
    "tags": [],
    "metadata": {
      "source": "Expense Tracker",
      "line_number": 9908,
      "reimbursable": false,
      "business_expense_marker": false
    }
  },
  {
    "transaction_date": "2022-10-06",
    "description": "Hotel: BKK",
    "merchant": "Ibis Styles",
    "amount": 118.38,
    "currency": "USD",
    "payment_method": "Credit Card: Chase Sapphire Reserve",
    "transaction_type": "expense",
    "tags": [],
    "metadata": {
      "source": "Expense Tracker",
      "line_number": 9909,
      "reimbursable": false,
      "business_expense_marker": false
    }
  },
  {
    "transaction_date": "2022-10-06",
    "description": "Taxi to Bar",
    "merchant": "Grab",
    "amount": 2.02,
    "currency": "USD",
    "payment_method": "Credit Card: Chase Sapphire Reserve",
    "transaction_type": "expense",
    "tags": [],
    "metadata": {
      "source": "Expense Tracker",
      "line_number": 9911,
      "reimbursable": false,
      "business_expense_marker": false
    }
  },
  {
    "transaction_date": "2022-10-06",
    "description": "Taxi to Lollipop",
    "merchant": "Grab",
    "amount": 2.05,
    "currency": "USD",
    "payment_method": "Credit Card: Chase Sapphire Reserve",
    "transaction_type": "expense",
    "tags": [],
    "metadata": {
      "source": "Expense Tracker",
      "line_number": 9914,
      "reimbursable": false,
      "business_expense_marker": false
    }
  },
  {
    "transaction_date": "2022-10-07",
    "description": "Taxi to airport",
    "merchant": "Grab",
    "amount": 8.14,
    "currency": "USD",
    "payment_method": "Credit Card: Chase Sapphire Reserve",
    "transaction_type": "expense",
    "tags": [],
    "metadata": {
      "source": "Expense Tracker",
      "line_number": 9919,
      "reimbursable": false,
      "business_expense_marker": false
    }
  },
  {
    "transaction_date": "2022-10-07",
    "description": "Taxi to Hotel",
    "merchant": "Grab",
    "amount": 15.8,
    "currency": "USD",
    "payment_method": "Credit Card: Chase Sapphire Reserve",
    "transaction_type": "expense",
    "tags": [],
    "metadata": {
      "source": "Expense Tracker",
      "line_number": 9920,
      "reimbursable": false,
      "business_expense_marker": false
    }
  },
  {
    "transaction_date": "2022-10-07",
    "description": "Topgolf",
    "merchant": "TopGolf",
    "amount": 95.62,
    "currency": "USD",
    "payment_method": "Credit Card: Chase Sapphire Reserve",
    "transaction_type": "expense",
    "tags": [],
    "metadata": {
      "source": "Expense Tracker",
      "line_number": 9925,
      "reimbursable": false,
      "business_expense_marker": false
    }
  },
  {
    "transaction_date": "2022-10-08",
    "description": "Monthly Subscription: Paramount+",
    "merchant": "CBS",
    "amount": 5.99,
    "currency": "USD",
    "payment_method": "Credit Card: Chase Sapphire Reserve",
    "transaction_type": "expense",
    "tags": [],
    "metadata": {
      "source": "Expense Tracker",
      "line_number": 9928,
      "reimbursable": false,
      "business_expense_marker": false
    }
  },
  {
    "transaction_date": "2022-10-08",
    "description": "LIV Golf Merchandise",
    "merchant": "LIV",
    "amount": 85.76,
    "currency": "USD",
    "payment_method": "Credit Card: Chase Sapphire Reserve",
    "transaction_type": "expense",
    "tags": [],
    "metadata": {
      "source": "Expense Tracker",
      "line_number": 9930,
      "reimbursable": false,
      "business_expense_marker": false
    }
  },
  {
    "transaction_date": "2022-10-08",
    "description": "Drinks",
    "merchant": "Nana",
    "amount": 83.21,
    "currency": "USD",
    "payment_method": "Credit Card: Chase Sapphire Reserve",
    "transaction_type": "expense",
    "tags": [],
    "metadata": {
      "source": "Expense Tracker",
      "line_number": 9939,
      "reimbursable": false,
      "business_expense_marker": false
    }
  },
  {
    "transaction_date": "2022-10-09",
    "description": "New Flight: BKK to CNX",
    "merchant": "AirAsia",
    "amount": 85.32,
    "currency": "USD",
    "payment_method": "Credit Card: Chase Sapphire Reserve",
    "transaction_type": "expense",
    "tags": [],
    "metadata": {
      "source": "Expense Tracker",
      "line_number": 9945,
      "reimbursable": false,
      "business_expense_marker": false
    }
  },
  {
    "transaction_date": "2022-10-09",
    "description": "Taxi to Condo",
    "merchant": "Grab",
    "amount": 7.72,
    "currency": "USD",
    "payment_method": "Credit Card: Chase Sapphire Reserve",
    "transaction_type": "expense",
    "tags": [],
    "metadata": {
      "source": "Expense Tracker",
      "line_number": 9946,
      "reimbursable": false,
      "business_expense_marker": false
    }
  },
  {
    "transaction_date": "2022-10-09",
    "description": "CNX Internet Bill",
    "merchant": "3BB",
    "amount": 20.07,
    "currency": "USD",
    "payment_method": "Credit Card: Chase Sapphire Reserve",
    "transaction_type": "expense",
    "tags": [],
    "metadata": {
      "source": "Expense Tracker",
      "line_number": 9949,
      "reimbursable": false,
      "business_expense_marker": false
    }
  },
  {
    "transaction_date": "2022-10-10",
    "description": "Taxi to Cafe",
    "merchant": "Grab",
    "amount": 3.62,
    "currency": "USD",
    "payment_method": "Credit Card: Chase Sapphire Reserve",
    "transaction_type": "expense",
    "tags": [],
    "metadata": {
      "source": "Expense Tracker",
      "line_number": 9955,
      "reimbursable": false,
      "business_expense_marker": false
    }
  },
  {
    "transaction_date": "2022-10-10",
    "description": "Gecko Spray, Lightning Cables",
    "merchant": "Lazada",
    "amount": 44.59,
    "currency": "USD",
    "payment_method": "Credit Card: Chase Sapphire Reserve",
    "transaction_type": "expense",
    "tags": [],
    "metadata": {
      "source": "Expense Tracker",
      "line_number": 9956,
      "reimbursable": false,
      "business_expense_marker": false
    }
  },
  {
    "transaction_date": "2022-10-10",
    "description": "Taxi to Condo",
    "merchant": "Grab",
    "amount": 2.73,
    "currency": "USD",
    "payment_method": "Bangkok Bank Account",
    "transaction_type": "expense",
    "tags": [],
    "metadata": {
      "source": "Expense Tracker",
      "line_number": 9958,
      "reimbursable": false,
      "business_expense_marker": false
    }
  },
  {
    "transaction_date": "2022-10-11",
    "description": "Monthly Subscription: YouTube Premium",
    "merchant": "Apple iTunes",
    "amount": 16.95,
    "currency": "USD",
    "payment_method": "Credit Card: Chase Sapphire Reserve",
    "transaction_type": "expense",
    "tags": [],
    "metadata": {
      "source": "Expense Tracker",
      "line_number": 9964,
      "reimbursable": false,
      "business_expense_marker": false
    }
  },
  {
    "transaction_date": "2022-10-12",
    "description": "Monthly Subscription: Netflix",
    "merchant": "Netflix",
    "amount": 21.19,
    "currency": "USD",
    "payment_method": "Credit Card: Chase Sapphire Reserve",
    "transaction_type": "expense",
    "tags": [],
    "metadata": {
      "source": "Expense Tracker",
      "line_number": 9973,
      "reimbursable": false,
      "business_expense_marker": false
    }
  },
  {
    "transaction_date": "2022-10-12",
    "description": "Taxi to Bike Shop",
    "merchant": "Grab",
    "amount": 1.92,
    "currency": "USD",
    "payment_method": "Credit Card: Chase Sapphire Reserve",
    "transaction_type": "expense",
    "tags": [],
    "metadata": {
      "source": "Expense Tracker",
      "line_number": 9975,
      "reimbursable": false,
      "business_expense_marker": false
    }
  },
  {
    "transaction_date": "2022-10-13",
    "description": "Fee",
    "merchant": "Wise",
    "amount": 4.53,
    "currency": "USD",
    "payment_method": "PNC Bank Account",
    "transaction_type": "expense",
    "tags": [],
    "metadata": {
      "source": "Expense Tracker",
      "line_number": 9984,
      "reimbursable": false,
      "business_expense_marker": false
    }
  },
  {
    "transaction_date": "2022-10-13",
    "description": "Phone",
    "merchant": "AIS",
    "amount": 11.28,
    "currency": "USD",
    "payment_method": "Credit Card: Chase Sapphire Reserve",
    "transaction_type": "expense",
    "tags": [],
    "metadata": {
      "source": "Expense Tracker",
      "line_number": 9989,
      "reimbursable": false,
      "business_expense_marker": false
    }
  },
  {
    "transaction_date": "2022-10-13",
    "description": "Golf Balls, Micro USB cable",
    "merchant": "Lazada",
    "amount": 75.4,
    "currency": "USD",
    "payment_method": "Credit Card: Chase Sapphire Reserve",
    "transaction_type": "expense",
    "tags": [],
    "metadata": {
      "source": "Expense Tracker",
      "line_number": 9990,
      "reimbursable": false,
      "business_expense_marker": false
    }
  },
  {
    "transaction_date": "2022-10-14",
    "description": "Drinks",
    "merchant": "Small World",
    "amount": 94.46,
    "currency": "USD",
    "payment_method": "Credit Card: Chase Sapphire Reserve",
    "transaction_type": "expense",
    "tags": [],
    "metadata": {
      "source": "Expense Tracker",
      "line_number": 10001,
      "reimbursable": false,
      "business_expense_marker": false
    }
  },
  {
    "transaction_date": "2022-10-19",
    "description": "Car Insurance",
    "merchant": "Travelers",
    "amount": 183,
    "currency": "USD",
    "payment_method": "Credit Card: Chase Sapphire Reserve",
    "transaction_type": "expense",
    "tags": [],
    "metadata": {
      "source": "Expense Tracker",
      "line_number": 10038,
      "reimbursable": false,
      "business_expense_marker": false
    }
  },
  {
    "transaction_date": "2022-10-19",
    "description": "Brunch: Gravity Cafe",
    "merchant": "Grab",
    "amount": 6.72,
    "currency": "USD",
    "payment_method": "Credit Card: Chase Sapphire Reserve",
    "transaction_type": "expense",
    "tags": [],
    "metadata": {
      "source": "Expense Tracker",
      "line_number": 10042,
      "reimbursable": false,
      "business_expense_marker": false
    }
  },
  {
    "transaction_date": "2022-10-19",
    "description": "Passport Renewal",
    "merchant": "pay.gov",
    "amount": 130,
    "currency": "USD",
    "payment_method": "Credit Card: Chase Sapphire Reserve",
    "transaction_type": "expense",
    "tags": [],
    "metadata": {
      "source": "Expense Tracker",
      "line_number": 10046,
      "reimbursable": false,
      "business_expense_marker": false
    }
  },
  {
    "transaction_date": "2022-10-22",
    "description": "Drinks",
    "merchant": "Small world",
    "amount": 155.87,
    "currency": "USD",
    "payment_method": "Credit Card: Chase Sapphire Reserve",
    "transaction_type": "expense",
    "tags": [],
    "metadata": {
      "source": "Expense Tracker",
      "line_number": 10082,
      "reimbursable": false,
      "business_expense_marker": false
    }
  },
  {
    "transaction_date": "2022-10-22",
    "description": "Monthly Subscription: Tinder",
    "merchant": "Apple",
    "amount": 26.49,
    "currency": "USD",
    "payment_method": "Credit Card: Chase Sapphire Reserve",
    "transaction_type": "expense",
    "tags": [],
    "metadata": {
      "source": "Expense Tracker",
      "line_number": 10083,
      "reimbursable": false,
      "business_expense_marker": false
    }
  },
  {
    "transaction_date": "2022-10-24",
    "description": "Monthly Subscription: iCloud",
    "merchant": "Apple iTunes",
    "amount": 9.99,
    "currency": "USD",
    "payment_method": "Credit Card: Chase Sapphire Reserve",
    "transaction_type": "expense",
    "tags": [],
    "metadata": {
      "source": "Expense Tracker",
      "line_number": 10095,
      "reimbursable": false,
      "business_expense_marker": false
    }
  },
  {
    "transaction_date": "2022-10-24",
    "description": "Monthly Subscription: WSJ",
    "merchant": "WSJ",
    "amount": 8,
    "currency": "USD",
    "payment_method": "Credit Card: Chase Sapphire Reserve",
    "transaction_type": "expense",
    "tags": [],
    "metadata": {
      "source": "Expense Tracker",
      "line_number": 10096,
      "reimbursable": false,
      "business_expense_marker": false
    }
  },
  {
    "transaction_date": "2022-10-24",
    "description": "Car Insurance",
    "merchant": "Travelers",
    "amount": 183,
    "currency": "USD",
    "payment_method": "Credit Card: Chase Sapphire Reserve",
    "transaction_type": "expense",
    "tags": [],
    "metadata": {
      "source": "Expense Tracker",
      "line_number": 10098,
      "reimbursable": false,
      "business_expense_marker": false
    }
  },
  {
    "transaction_date": "2022-10-25",
    "description": "Monthly Subscription: HBO NOW",
    "merchant": "Apple",
    "amount": 15.89,
    "currency": "USD",
    "payment_method": "Credit Card: Chase Sapphire Reserve",
    "transaction_type": "expense",
    "tags": [],
    "metadata": {
      "source": "Expense Tracker",
      "line_number": 10106,
      "reimbursable": false,
      "business_expense_marker": false
    }
  },
  {
    "transaction_date": "2022-10-27",
    "description": "Aftershave, cleaning supplies",
    "merchant": "Lazada",
    "amount": 48.54,
    "currency": "USD",
    "payment_method": "Credit Card: Chase Sapphire Reserve",
    "transaction_type": "expense",
    "tags": [],
    "metadata": {
      "source": "Expense Tracker",
      "line_number": 10121,
      "reimbursable": false,
      "business_expense_marker": false
    }
  },
  {
    "transaction_date": "2022-10-29",
    "description": "Cell Phone",
    "merchant": "T-Mobile",
    "amount": 71.04,
    "currency": "USD",
    "payment_method": "Credit Card: Chase Sapphire Reserve",
    "transaction_type": "expense",
    "tags": [],
    "metadata": {
      "source": "Expense Tracker",
      "line_number": 10140,
      "reimbursable": false,
      "business_expense_marker": false
    }
  },
  {
    "transaction_date": "2022-10-29",
    "description": "Shaving Soap",
    "merchant": "Lazada",
    "amount": 12.41,
    "currency": "USD",
    "payment_method": "Credit Card: Chase Sapphire Reserve",
    "transaction_type": "expense",
    "tags": [],
    "metadata": {
      "source": "Expense Tracker",
      "line_number": 10141,
      "reimbursable": false,
      "business_expense_marker": false
    }
  },
  {
    "transaction_date": "2022-10-31",
    "description": "Hotel: BKK",
    "merchant": "hotels.com",
    "amount": 128.19,
    "currency": "USD",
    "payment_method": "Credit Card: Chase Sapphire Reserve",
    "transaction_type": "expense",
    "tags": [],
    "metadata": {
      "source": "Expense Tracker",
      "line_number": 10156,
      "reimbursable": false,
      "business_expense_marker": false
    }
  },
  {
    "transaction_date": "2022-10-31",
    "description": "Flight: CNX - BKK",
    "merchant": "AirAsia",
    "amount": 63.69,
    "currency": "USD",
    "payment_method": "Credit Card: Chase Sapphire Reserve",
    "transaction_type": "expense",
    "tags": [],
    "metadata": {
      "source": "Expense Tracker",
      "line_number": 10157,
      "reimbursable": false,
      "business_expense_marker": false
    }
  },
  {
    "transaction_date": "2022-10-31",
    "description": "Flight: BKK - CNX",
    "merchant": "AirAsia",
    "amount": 55.26,
    "currency": "USD",
    "payment_method": "Credit Card: Chase Sapphire Reserve",
    "transaction_type": "expense",
    "tags": [],
    "metadata": {
      "source": "Expense Tracker",
      "line_number": 10158,
      "reimbursable": false,
      "business_expense_marker": false
    }
  },
  {
    "transaction_date": "2022-10-14",
    "description": "Paycheck",
    "merchant": "e2open",
    "amount": 2972.43,
    "currency": "USD",
    "payment_method": "Direct Deposit",
    "transaction_type": "income",
    "tags": [],
    "metadata": {
      "source": "Gross Income",
      "line_number": 10164
    }
  },
  {
    "transaction_date": "2022-10-31",
    "description": "Paycheck",
    "merchant": "e2open",
    "amount": 2972.43,
    "currency": "USD",
    "payment_method": "Direct Deposit",
    "transaction_type": "income",
    "tags": [],
    "metadata": {
      "source": "Gross Income",
      "line_number": 10165
    }
  },
  {
    "transaction_date": "2022-10-31",
    "description": "Emergency Savings",
    "merchant": "Vanguard",
    "amount": 341.67,
    "currency": "USD",
    "payment_method": "PNC Bank Account",
    "transaction_type": "expense",
    "tags": [
      "Savings/Investment"
    ],
    "metadata": {
      "source": "Personal Savings & Investments",
      "line_number": 10173
    }
  }
]